model_auditor/__init__.py
model_auditor/core.py
model_auditor/metric_inputs.py
model_auditor/metrics.py
model_auditor/schemas.py
model_auditor/utils.py
model_auditor/plotting/__init__.py
model_auditor/plotting/plotters.py
model_auditor/plotting/schemas.py
model_auditor-0.1.2.dist-info/METADATA
model_auditor-0.1.2.dist-info/WHEEL
model_auditor-0.1.2.dist-info/top_level.txt
model_auditor-0.1.2.dist-info/RECORD
