Metadata-Version: 2.4
Name: model-auditor
Version: 0.1.2
Requires-Dist: pandas>=2.2
Requires-Dist: numpy>=2.1
Requires-Dist: scikit-learn>=1.5
